rquote/__init__.py
rquote/config.py
rquote/exceptions.py
rquote/plots.py
rquote/utils.py
rquote/api/__init__.py
rquote/api/lists.py
rquote/api/price.py
rquote/api/stock_info.py
rquote/api/tick.py
rquote/cache/__init__.py
rquote/cache/base.py
rquote/cache/memory.py
rquote/cache/persistent.py
rquote/data_sources/__init__.py
rquote/data_sources/base.py
rquote/data_sources/sina.py
rquote/data_sources/tencent.py
rquote/factors/__init__.py
rquote/factors/technical.py
rquote/markets/__init__.py
rquote/markets/base.py
rquote/markets/cn_stock.py
rquote/markets/factory.py
rquote/markets/future.py
rquote/markets/hk_stock.py
rquote/markets/us_stock.py
rquote/parsers/__init__.py
rquote/parsers/kline.py
rquote/utils/__init__.py
rquote/utils/date.py
rquote/utils/helpers.py
rquote/utils/http.py
rquote/utils/logging.py
rquote/utils/web.py
rquote-0.4.6.dist-info/METADATA
rquote-0.4.6.dist-info/WHEEL
rquote-0.4.6.dist-info/top_level.txt
rquote-0.4.6.dist-info/RECORD
