Metadata-Version: 2.4
Name: rquote
Version: 0.4.6
Summary: Mostly day quotes of cn/hk/us/fund/future markets, side with quote list fetch
Requires-Python: >=3.9.0
Requires-Dist: build>=0.9.0
Requires-Dist: httpx>=0.20.0
Requires-Dist: pandas>=1.0.0
Requires-Dist: setuptools>=42
Requires-Dist: twine>=3.8.0
Provides-Extra: persistent
Requires-Dist: duckdb>=0.9.0; extra == "persistent"
